agentmail_mcp/__init__.py
agentmail_mcp/server.py
agentmail_mcp/test_imports.py
agentmail_mcp/tools/__init__.py
agentmail_mcp/tools/email.py
agentmail_mcp-0.3.0.dist-info/METADATA
agentmail_mcp-0.3.0.dist-info/WHEEL
agentmail_mcp-0.3.0.dist-info/entry_points.txt
agentmail_mcp-0.3.0.dist-info/licenses/LICENSE
agentmail_mcp-0.3.0.dist-info/RECORD
