Metadata-Version: 2.4
Name: agentmail-mcp
Version: 0.3.0
Summary: AgentMail MCP server for AI assistant email integration
Project-URL: Homepage, https://agentmail.to/
Project-URL: Bug Tracker, https://github.com/agentmail-to/agentmail-toolkit
Author-email: Michael Kim <michael@agentmail.to>
License-File: LICENSE
Requires-Python: >=3.10
Requires-Dist: agentmail>=0.0.17
Requires-Dist: fastmcp>=0.4.0
Requires-Dist: httpx>=0.28.1
Requires-Dist: mcp>=1.0.0
Requires-Dist: mcp[cli]>=1.4.1
Requires-Dist: python-dotenv>=1.0.0
